StarRailGPS/__init__.py
StarRailGPS/gps.py
StarRailGPS/map_crawler.py
StarRailGPS/remove_uid.py
StarRailGPS/scales.py
StarRailGPS/resources/imgs/arrow.jpg
StarRailGPS/resources/maps/38.png
StarRailGPS/resources/maps/39.png
StarRailGPS/resources/maps/43.png
StarRailGPS/resources/maps/44.png
StarRailGPS/resources/maps/45.png
StarRailGPS/resources/maps/46.png
StarRailGPS/resources/maps/47.png
StarRailGPS/resources/maps/48.png
StarRailGPS/resources/maps/49.png
StarRailGPS/resources/maps/50.png
StarRailGPS/resources/maps/51.png
StarRailGPS/resources/maps/52.png
StarRailGPS/resources/maps/53.png
StarRailGPS/resources/maps/54.png
StarRailGPS/resources/maps/55.png
StarRailGPS/resources/maps/56.png
StarRailGPS/resources/maps/57.png
StarRailGPS/resources/maps/58.png
StarRailGPS/resources/maps/59.png
StarRailGPS/resources/maps/60.png
StarRailGPS/resources/maps/61.png
StarRailGPS/resources/maps/62.png
StarRailGPS/resources/maps/63.png
StarRailGPS/resources/maps/64.png
StarRailGPS/resources/maps/66.png
StarRailGPS/resources/maps/67.png
StarRailGPS/resources/maps/68.png
StarRailGPS/resources/maps/69.png
StarRailGPS/resources/maps/name_id.json
StarRailGPS/resources/maps/tree.json
StarRailGPS/resources/test_data/screen_1920_1080.png
StarRailGPS/resources/test_data/screen_1920_1080_1.png
StarRailGPS/resources/test_data/screen_1920_1080_run.png
StarRailGPS/utils/__init__.py
StarRailGPS/utils/resources.py
StarRailGPS-1.0.4.dist-info/METADATA
StarRailGPS-1.0.4.dist-info/WHEEL
StarRailGPS-1.0.4.dist-info/top_level.txt
StarRailGPS-1.0.4.dist-info/RECORD
