Metadata-Version: 2.1
Name: StarRailGPS
Version: 1.0.4
Summary: Honkai: Star Rail GPS
Home-page: https://github.com/furacas/StarRailGPS
Author: furacas
Author-email: s.furacas@outlook.com
Classifier: Programming Language :: Python :: 3
Requires-Python: >=3.7
Requires-Dist: opencv-python
Requires-Dist: numpy
Requires-Dist: requests
Requires-Dist: setuptools
